[{"userInfo":{"firstName":"Hickory","lastName":"Biggins","password":"loveTrees84","freqflyer":false,"age":42,"username":"TreeHugger42"},"userId":"cd12fd2c-27e6-4ac3-ac86-2e866a8ab422","partyMembers":[{"firstName":"Jimmy","lastName":"Taylorson","age":41},{"firstName":"Albany","lastName":"Creek","age":40},{"firstName":"Jeremiah","lastName":"Truingdale","age":43}]},{"userInfo":{"firstName":"Samantha","lastName":"Paramount","password":"amogusSUS","freqflyer":false,"age":23,"username":"CringyBass25"},"userId":"86a56bc3-cf2e-4885-a46c-bcc51e1aef02","partyMembers":[{"firstName":"Tiffany","lastName":"Stellar","age":22},{"firstName":"Kylie","lastName":"Lormont","age":23},{"firstName":"Jocelyn","lastName":"Galore","age":24}]},{"userInfo":{"firstName":"Billy","lastName":"Jean","password":"notTheSameArtist","freqflyer":false,"age":27,"username":"AnnieRUOkay"},"userId":"c1aafa1c-dc0f-4bc3-a097-9f1283aab923","partyMembers":[{"firstName":"Franklin","lastName":"Stevens","age":28},{"firstName":"Jillian","lastName":"Collardsworth","age":27},{"firstName":"gary","lastName":"Gygax","age":28}]},{"userInfo":{"firstName":"Gillian","lastName":"Gilmore","password":"guessGoosesGyrate","freqflyer":false,"age":32,"username":"GilgameshGotGame"},"userId":"8fe14d28-0e55-4acf-ac7a-ebc69b9fb393","partyMembers":[{"firstName":"Hildegard","lastName":"Hendricksson","age":33},{"firstName":"Godfried","lastName":"Lillacant","age":31},{"firstName":"Steve","lastName":"Steven","age":32}]}]